LICENSE
MANIFEST.in
NOTICE
README.md
setup.cfg
setup.py
pyramid_restful/__init__.py
pyramid_restful/decorators.py
pyramid_restful/exceptions.py
pyramid_restful/expandables.py
pyramid_restful/filters.py
pyramid_restful/generics.py
pyramid_restful/mixins.py
pyramid_restful/permissions.py
pyramid_restful/routers.py
pyramid_restful/settings.py
pyramid_restful/views.py
pyramid_restful/viewsets.py
pyramid_restful/pagination/__init__.py
pyramid_restful/pagination/base.py
pyramid_restful/pagination/linkheader.py
pyramid_restful/pagination/pagenumber.py
pyramid_restful/pagination/utilities.py
pyramid_restful_framework.egg-info/PKG-INFO
pyramid_restful_framework.egg-info/SOURCES.txt
pyramid_restful_framework.egg-info/dependency_links.txt
pyramid_restful_framework.egg-info/requires.txt
pyramid_restful_framework.egg-info/top_level.txt