Metadata-Version: 1.1
Name: pyramid-restful-framework
Version: 0.14.1
Summary: RESTful API framework for Pyramid.
Home-page: https://github.com/danpoland/pyramid-restful-framework
Author: Daniel Poland
Author-email: danpoland84@gmail.com
License: BSD
Platform: UNKNOWN
Classifier: Development Status :: 3 - Alpha
Classifier: Environment :: Web Environment
Classifier: Framework :: Pyramid
Classifier: Intended Audience :: Developers
Classifier: License :: OSI Approved :: BSD License
Classifier: Operating System :: OS Independent
Classifier: Programming Language :: Python
Classifier: Topic :: Internet :: WWW/HTTP
